awslabs/__init__.py
awslabs/git_repo_research_mcp_server/__init__.py
awslabs/git_repo_research_mcp_server/defaults.py
awslabs/git_repo_research_mcp_server/embeddings.py
awslabs/git_repo_research_mcp_server/github_search.py
awslabs/git_repo_research_mcp_server/indexer.py
awslabs/git_repo_research_mcp_server/models.py
awslabs/git_repo_research_mcp_server/repository.py
awslabs/git_repo_research_mcp_server/search.py
awslabs/git_repo_research_mcp_server/server.py
awslabs/git_repo_research_mcp_server/utils.py
awslabs_git_repo_research_mcp_server-1.0.11.dist-info/METADATA
awslabs_git_repo_research_mcp_server-1.0.11.dist-info/WHEEL
awslabs_git_repo_research_mcp_server-1.0.11.dist-info/entry_points.txt
awslabs_git_repo_research_mcp_server-1.0.11.dist-info/licenses/LICENSE
awslabs_git_repo_research_mcp_server-1.0.11.dist-info/licenses/NOTICE
awslabs_git_repo_research_mcp_server-1.0.11.dist-info/RECORD
