Metadata-Version: 2.4
Name: awslabs.git-repo-research-mcp-server
Version: 1.0.11
Summary: An AWS Labs Model Context Protocol (MCP) server for researching git repositories
Project-URL: Homepage, https://awslabs.github.io/mcp/
Project-URL: Documentation, https://awslabs.github.io/mcp/servers/git-repo-research-mcp-server/
Project-URL: Source, https://github.com/awslabs/mcp.git
Project-URL: Bug Tracker, https://github.com/awslabs/mcp/issues
Project-URL: Changelog, https://github.com/awslabs/mcp/blob/main/src/git-repo-research-mcp-server/CHANGELOG.md
Author: Amazon Web Services
Author-email: AWSLabs MCP <203918161+awslabs-mcp@users.noreply.github.com>
License: Apache-2.0
License-File: LICENSE
License-File: NOTICE
Classifier: License :: OSI Approved :: Apache Software License
Classifier: Operating System :: OS Independent
Classifier: Programming Language :: Python
Classifier: Programming Language :: Python :: 3
Classifier: Programming Language :: Python :: 3.10
Classifier: Programming Language :: Python :: 3.11
Classifier: Programming Language :: Python :: 3.12
Classifier: Programming Language :: Python :: 3.13
Requires-Python: >=3.10
Requires-Dist: backoff>=2.2.1
Requires-Dist: boto3>=1.37.26
Requires-Dist: faiss-cpu>=1.10.0
Requires-Dist: gitpython>=3.1.44
Requires-Dist: h11>=0.16.0
Requires-Dist: langchain-aws>=0.2.18
Requires-Dist: langchain-community>=0.3.20
Requires-Dist: langchain>=0.3.22
Requires-Dist: loguru>=0.7.3
Requires-Dist: mcp[cli]>=1.23.0
Requires-Dist: pydantic>=2.10.6
Requires-Dist: requests>=2.32.0
